README.md
pyproject.toml
setup.cfg
setup.py
bf_banki_nlu.egg-info/PKG-INFO
bf_banki_nlu.egg-info/SOURCES.txt
bf_banki_nlu.egg-info/dependency_links.txt
bf_banki_nlu.egg-info/entry_points.txt
bf_banki_nlu.egg-info/requires.txt
bf_banki_nlu.egg-info/top_level.txt
examples/__init__.py
examples/nlg_server/__init__.py
examples/nlg_server/nlg_server.py
rasa/__init__.py
rasa/__main__.py
rasa/api.py
rasa/constants.py
rasa/exceptions.py
rasa/jupyter.py
rasa/model.py
rasa/model_testing.py
rasa/model_training.py
rasa/server.py
rasa/telemetry.py
rasa/validator.py
rasa/version.py
rasa/cli/__init__.py
rasa/cli/data.py
rasa/cli/evaluate.py
rasa/cli/export.py
rasa/cli/interactive.py
rasa/cli/run.py
rasa/cli/scaffold.py
rasa/cli/shell.py
rasa/cli/telemetry.py
rasa/cli/test.py
rasa/cli/train.py
rasa/cli/utils.py
rasa/cli/visualize.py
rasa/cli/x.py
rasa/cli/arguments/__init__.py
rasa/cli/arguments/data.py
rasa/cli/arguments/default_arguments.py
rasa/cli/arguments/evaluate.py
rasa/cli/arguments/export.py
rasa/cli/arguments/interactive.py
rasa/cli/arguments/run.py
rasa/cli/arguments/shell.py
rasa/cli/arguments/test.py
rasa/cli/arguments/train.py
rasa/cli/arguments/visualize.py
rasa/cli/arguments/x.py
rasa/core/__init__.py
rasa/core/agent.py
rasa/core/constants.py
rasa/core/exceptions.py
rasa/core/exporter.py
rasa/core/http_interpreter.py
rasa/core/jobs.py
rasa/core/lock.py
rasa/core/lock_store.py
rasa/core/migrate.py
rasa/core/processor.py
rasa/core/run.py
rasa/core/test.py
rasa/core/tracker_store.py
rasa/core/train.py
rasa/core/utils.py
rasa/core/visualize.py
rasa/core/actions/__init__.py
rasa/core/actions/action.py
rasa/core/actions/forms.py
rasa/core/actions/loops.py
rasa/core/actions/two_stage_fallback.py
rasa/core/brokers/__init__.py
rasa/core/brokers/broker.py
rasa/core/brokers/file.py
rasa/core/brokers/kafka.py
rasa/core/brokers/pika.py
rasa/core/brokers/sql.py
rasa/core/channels/__init__.py
rasa/core/channels/botframework.py
rasa/core/channels/callback.py
rasa/core/channels/channel.py
rasa/core/channels/console.py
rasa/core/channels/facebook.py
rasa/core/channels/hangouts.py
rasa/core/channels/mattermost.py
rasa/core/channels/rasa_chat.py
rasa/core/channels/rest.py
