Metadata-Version: 2.1
Name: bf-banki-nlu
Version: 1.5
Summary: UNKNOWN
Home-page: https://botsfactory.com
Author: Botsfactory
Author-email: boutaina.j@gmail.com
Maintainer: BF
Maintainer-email: boutaina.j@gmail.com
License: Apache 2.0
Download-URL: https://gitlab.com/boutaina.jam/oncf_backend.git
Project-URL: Bug Reports, https://gitlab.com/boutaina.jam/oncf_backend.git
Project-URL: Source, https://gitlab.com/boutaina.jam/oncf_backend.git
Keywords: nlp machine-learning machine-learning-library bot bots botkit rasa conversational-agents conversational-ai chatbotchatbot-framework bot-framework
Platform: UNKNOWN
Classifier: Development Status :: 4 - Beta
Classifier: Intended Audience :: Developers
Classifier: License :: OSI Approved :: Apache Software License
Classifier: Programming Language :: Python
Classifier: Programming Language :: Python :: 3.6
Classifier: Programming Language :: Python :: 3.7
Classifier: Topic :: Software Development :: Libraries
Requires-Python: >=3.6
Provides-Extra: test
